<?xml version="1.0" ?>
<State openmmVersion="8.0" stepCount="0" time="0" type="State" version="1">
	<PeriodicBoxVectors>
		<A x="10" y="0" z="0"/>
		<B x="0" y="10" z="0"/>
		<C x="0" y="0" z="10"/>
	</PeriodicBoxVectors>
	<Parameters/>
	<Energies KineticEnergy="0" PotentialEnergy="5556379274.0584"/>
	<Positions>
		<Position x="-.37299999594688416" y=".07680034637451172" z="-.06719999760389328"/>
		<Position x="-.3328999876976013" y="-.010499954223632812" z=".04309999942779541"/>
		<Position x="-.1973000019788742" y="-.07870006561279297" z=".018000001087784767"/>
		<Position x="-.07999999821186066" y=".020400047302246094" z=".02029999904334545"/>
		<Position x=".05420000106096268" y="-.053000450134277344" z=".009200000204145908"/>
		<Position x=".171300008893013" y=".04590034484863281" z=".010199999436736107"/>
		<Position x=".30539998412132263" y="-.027199745178222656" z="-.0006000000284984708"/>
		<Position x=".41519999504089355" y=".06890010833740234" z="-.0017000001389533281"/>
		<Position x=".4223000109195709" y=".11149978637695312" z=".09359999746084213"/>
		<Position x=".307699978351593" y="-.08609962463378906" z="-.09489999711513519"/>
		<Position x=".3176000118255615" y="-.09729957580566406" z=".08510000258684158"/>
		<Position x=".16920000314712524" y=".10470008850097656" z=".10470000654459"/>
		<Position x=".16130000352859497" y=".11629962921142578" z="-.07530000060796738"/>
		<Position x=".056300003081560135" y="-.11159992218017578" z="-.08529999852180481"/>
		<Position x=".06480000168085098" y="-.12339973449707031" z=".09470000118017197"/>
		<Position x="-.0892999991774559" y=".09119987487792969" z="-.0648999959230423"/>
		<Position x="-.08240000158548355" y=".078399658203125" z=".1151999980211258"/>
		<Position x="-.1818999946117401" y="-.1546001434326172" z=".09780000150203705"/>
		<Position x="-.19949999451637268" y="-.13230037689208984" z="-.07940000295639038"/>
		<Position x="-.3295000195503235" y=".04790019989013672" z=".13760000467300415"/>
		<Position x="-.41030001640319824" y="-.08920001983642578" z=".05550000071525574"/>
		<Position x="-.31029999256134033" y=".160400390625" z="-.06949999928474426"/>
		<Position x=".5056000351905823" y=".014699935913085938" z="-.017400000244379044"/>
		<Position x=".5945000052452087" y=".0651998519897461" z="-.08399999886751175"/>
		<Position x=".5245000123977661" y="-.1220998764038086" z=".041200000792741776"/>
		<Position x=".4010000228881836" y="-.1660003662109375" z=".12079999595880508"/>
		<Position x=".42090001702308655" y="-.3058004379272461" z=".18050000071525574"/>
		<Position x=".29749998450279236" y="-.3496999740600586" z=".25999999046325684"/>
		<Position x=".3163999915122986" y="-.4864997863769531" z=".31859999895095825"/>
		<Position x=".22750000655651093" y="-.5369997024536133" z=".3852999806404114"/>
		<Position x=".27869999408721924" y="-.27770042419433594" z=".342600017786026"/>
		<Position x=".2085999995470047" y="-.3513002395629883" z=".1932000070810318"/>
		<Position x=".5094999670982361" y="-.3049001693725586" z=".24770000576972961"/>
		<Position x=".43950000405311584" y="-.3786001205444336" z=".09840000420808792"/>
		<Position x=".3824999928474426" y="-.0931997299194336" z=".2029000073671341"/>
		<Position x=".3124000132083893" y="-.1668996810913086" z=".05350000411272049"/>
		<Position x=".6132999658584595" y="-.1204996109008789" z=".1080000028014183"/>
		<Position x=".5433000326156616" y="-.19410037994384766" z="-.04129999876022339"/>
		<Position x="-.36250001192092896" y=".025600433349609375" z="-.15779998898506165"/>
		<Position x="-.29839998483657837" y=".1128997802734375" z="-.25599998235702515"/>
		<Position x="-.1720000058412552" y=".18109989166259766" z="-.20069999992847443"/>
		<Position x="-.05739999935030937" y=".0819997787475586" z="-.17630000412464142"/>
		<Position x=".07079999893903732" y=".15540027618408203" z="-.13490000367164612"/>
		<Position x=".1850999891757965" y=".05650043487548828" z="-.10930000245571136"/>
		<Position x=".3131999969482422" y=".12959957122802734" z="-.0681999996304512"/>
		<Position x=".4197999835014343" y=".033499717712402344" z="-.042100001126527786"/>
		<Position x=".5026999711990356" y=".086700439453125" z="-.006899999920278788"/>
		<Position x=".44850000739097595" y="-.009099960327148438" z="-.13329999148845673"/>
		<Position x=".2939999997615814" y=".18850040435791016" z=".02419999986886978"/>
		<Position x=".34460002183914185" y=".19970035552978516" z="-.14890000224113464"/>
		<Position x=".2046000063419342" y="-.002300262451171875" z="-.20170000195503235"/>
		<Position x=".1559000015258789" y="-.013899803161621094" z="-.028200000524520874"/>
		<Position x=".05130000039935112" y=".21399974822998047" z="-.042399998754262924"/>
		<Position x=".10060000419616699" y=".225799560546875" z="-.21570000052452087"/>
		<Position x="-.08579999953508377" y=".011199951171875" z="-.09539999812841415"/>
		<Position x="-.038100000470876694" y=".024000167846679688" z="-.26919999718666077"/>
		<Position x="-.1389000117778778" y=".2569999694824219" z="-.2750000059604645"/>
		<Position x="-.1964000016450882" y=".23470020294189453" z="-.10639999806880951"/>
		<Position x="-.273499995470047" y=".05449962615966797" z="-.3472999930381775"/>
		<Position x="-.3709999918937683" y=".19159984588623047" z="-.2858000099658966"/>
		<Position x="-.3021000027656555" y="-.057999610900878906" z="-.141199991106987"/>
		<Position x=".4083999991416931" y="-.5417003631591797" z=".3026999831199646"/>
		<Position x=".49710002541542053" y="-.5364999771118164" z=".3865000009536743"/>
		<Position x=".42670002579689026" y="-.6220998764038086" z=".17749999463558197"/>
		<Position x=".4374000132083893" y="-.7715997695922852" z=".20940001308918"/>
		<Position x=".4531000256538391" y="-.8542995452880859" z=".08089999854564667"/>
		<Position x=".4705999791622162" y="-1.0038995742797852" z=".10980000346899033"/>
		<Position x=".34540000557899475" y="-1.0648002624511719" z=".16510000824928284"/>
		<Position x=".2502000033855438" y="-1.0943002700805664" z=".08810000121593475"/>
		<Position x=".33320000767707825" y="-1.0859003067016602" z=".3021000027656555"/>
		<Position x=".24869999289512634" y="-1.1258001327514648" z=".34119999408721924"/>
		<Position x=".5546000003814697" y="-1.0194997787475586" z=".18090000748634338"/>
		<Position x=".49699997901916504" y="-1.0560998916625977" z=".015199999324977398"/>
		<Position x=".5430999994277954" y="-.8187999725341797" z=".02590000070631504"/>
		<Position x=".36489999294281006" y="-.8389997482299805" z=".014900000765919685"/>
		<Position x=".5252000093460083" y="-.7891998291015625" z=".275299996137619"/>
		<Position x=".3456000089645386" y="-.8037996292114258" z=".26340001821517944"/>
		<Position x=".33970001339912415" y="-.6044998168945312" z=".11059999465942383"/>
		<Position x=".5185999870300293" y="-.5875997543334961" z=".12530000507831573"/>
	</Positions>
	<Velocities>
		<Velocity x="0" y="0" z="0"/>
		<Velocity x="0" y="0" z="0"/>
		<Velocity x="0" y="0" z="0"/>
		<Velocity x="0" y="0" z="0"/>
		<Velocity x="0" y="0" z="0"/>
		<Velocity x="0" y="0" z="0"/>
		<Velocity x="0" y="0" z="0"/>
		<Velocity x="0" y="0" z="0"/>
		<Velocity x="0" y="0" z="0"/>
		<Velocity x="0" y="0" z="0"/>
		<Velocity x="0" y="0" z="0"/>
		<Velocity x="0" y="0" z="0"/>
		<Velocity x="0" y="0" z="0"/>
		<Velocity x="0" y="0" z="0"/>
		<Velocity x="0" y="0" z="0"/>
		<Velocity x="0" y="0" z="0"/>
		<Velocity x="0" y="0" z="0"/>
		<Velocity x="0" y="0" z="0"/>
		<Velocity x="0" y="0" z="0"/>
		<Velocity x="0" y="0" z="0"/>
		<Velocity x="0" y="0" z="0"/>
		<Velocity x="0" y="0" z="0"/>
		<Velocity x="0" y="0" z="0"/>
		<Velocity x="0" y="0" z="0"/>
		<Velocity x="0" y="0" z="0"/>
		<Velocity x="0" y="0" z="0"/>
		<Velocity x="0" y="0" z="0"/>
		<Velocity x="0" y="0" z="0"/>
		<Velocity x="0" y="0" z="0"/>
		<Velocity x="0" y="0" z="0"/>
		<Velocity x="0" y="0" z="0"/>
		<Velocity x="0" y="0" z="0"/>
		<Velocity x="0" y="0" z="0"/>
		<Velocity x="0" y="0" z="0"/>
		<Velocity x="0" y="0" z="0"/>
		<Velocity x="0" y="0" z="0"/>
		<Velocity x="0" y="0" z="0"/>
		<Velocity x="0" y="0" z="0"/>
		<Velocity x="0" y="0" z="0"/>
		<Velocity x="0" y="0" z="0"/>
		<Velocity x="0" y="0" z="0"/>
		<Velocity x="0" y="0" z="0"/>
		<Velocity x="0" y="0" z="0"/>
		<Velocity x="0" y="0" z="0"/>
		<Velocity x="0" y="0" z="0"/>
		<Velocity x="0" y="0" z="0"/>
		<Velocity x="0" y="0" z="0"/>
		<Velocity x="0" y="0" z="0"/>
		<Velocity x="0" y="0" z="0"/>
		<Velocity x="0" y="0" z="0"/>
		<Velocity x="0" y="0" z="0"/>
		<Velocity x="0" y="0" z="0"/>
		<Velocity x="0" y="0" z="0"/>
		<Velocity x="0" y="0" z="0"/>
		<Velocity x="0" y="0" z="0"/>
		<Velocity x="0" y="0" z="0"/>
		<Velocity x="0" y="0" z="0"/>
		<Velocity x="0" y="0" z="0"/>
		<Velocity x="0" y="0" z="0"/>
		<Velocity x="0" y="0" z="0"/>
		<Velocity x="0" y="0" z="0"/>
		<Velocity x="0" y="0" z="0"/>
		<Velocity x="0" y="0" z="0"/>
		<Velocity x="0" y="0" z="0"/>
		<Velocity x="0" y="0" z="0"/>
		<Velocity x="0" y="0" z="0"/>
		<Velocity x="0" y="0" z="0"/>
		<Velocity x="0" y="0" z="0"/>
		<Velocity x="0" y="0" z="0"/>
		<Velocity x="0" y="0" z="0"/>
		<Velocity x="0" y="0" z="0"/>
		<Velocity x="0" y="0" z="0"/>
		<Velocity x="0" y="0" z="0"/>
		<Velocity x="0" y="0" z="0"/>
		<Velocity x="0" y="0" z="0"/>
		<Velocity x="0" y="0" z="0"/>
		<Velocity x="0" y="0" z="0"/>
		<Velocity x="0" y="0" z="0"/>
		<Velocity x="0" y="0" z="0"/>
	</Velocities>
	<Forces>
		<Force x="-909.2813143134117" y="6805.077692210674" z="11413.725755125284"/>
		<Force x="-636.6836865465157" y="-214.05471742735244" z="963.9033712476958"/>
		<Force x="-10558.928613756318" y="-9897.163677056786" z="11926.223341539968"/>
		<Force x="322094.6569441976" y="508342.5379834657" z="6579840.898022529"/>
		<Force x="-6512532.815114403" y="-2526982.841085096" z="2421978.6766834594"/>
		<Force x="613341102.870329" y="-2147482970.5430622" z="1583014252.7081778"/>
		<Force x="-6545888.325036838" y="-3888724.516052801" z="2691061.06472951"/>
		<Force x="2147472870.1471856" y="-2147477543.5396638" z="-2147479950.8792024"/>
		<Force x="-382.9343581474386" y="754.5655895024538" z="463.27854957897216"/>
		<Force x="-10511.152507265564" y="-30917.815394103527" z="-10196.881879420951"/>
		<Force x="1374711.4554234594" y="99974181.33463383" z="40755716.620983176"/>
		<Force x="-2753.8208478353918" y="-385.9188541341573" z="4785.493542606244"/>
		<Force x="-936559569.5485123" y="2147483358.0889132" z="1349736867.4848228"/>
		<Force x="-12182.284439958632" y="-14069.623608339578" z="-5636.255418092012"/>
		<Force x="-522.3305517844856" y="-271.21254336833954" z="192.73478252626956"/>
		<Force x="-2928387.3861569325" y="26270248.000764176" z="16119060.15843744"/>
		<Force x="-30.140625402797014" y="-203.38513823598623" z="-334.98505624523386"/>
		<Force x="-76.18900833651423" y="342.2350753247738" z="-384.7121640602127"/>
		<Force x="-112.91649097204208" y="-1394.9854406937957" z="1025.500367789995"/>
		<Force x="-28.28170883283019" y="-275.6048626899719" z="-402.8261446803808"/>
		<Force x="269.5286095440388" y="302.98314122855663" z="38.27551729977131"/>
		<Force x="-1416.746178660076" y="-897.8258273415267" z="771.3373303636909"/>
		<Force x="1469262054.8844237" y="-411301522.26341283" z="408800695.2207949"/>
		<Force x="161983.39714308036" y="13804.979204368079" z="-61011.12882904569"/>
		<Force x="23965.653855445096" y="-30673.64160077623" z="15472.7680050747"/>
		<Force x="5722744.573321784" y="-4726519.043889174" z="2465329.7219052883"/>
		<Force x="612.0849922143389" y="246.78473940049298" z="-414.3555595523212"/>
		<Force x="-851.696793780895" y="1296.6478153900243" z="-388.00933446059935"/>
		<Force x="-7273.196987594245" y="3876.0618088613264" z="1947.7387104264926"/>
		<Force x="-1165.652275845874" y="186.37895378191024" z="20.013554685749114"/>
		<Force x="52.187836334109306" y="-417.9096524696797" z="-362.4730800902471"/>
		<Force x="409.6822182685137" y="-8.257625166326761" z="424.93289313465357"/>
		<Force x="-280.7209127936512" y="106.08762923348695" z="-351.1307836510241"/>
		<Force x="-2.758575603365898" y="700.5584803875536" z="233.00582390697673"/>
		<Force x="33475.855602651834" y="1403.6429631570354" z="60714.80368801998"/>
		<Force x="-7106721.288958253" y="-95498846.56638218" z="-43168279.737880334"/>
		<Force x="-409.191511657089" y="20.610189091414213" z="-413.12051182985306"/>
		<Force x="35.14094389975071" y="335.7558455616236" z="404.7181247761473"/>
		<Force x="1682.4597651064396" y="-6792.5331184268" z="-11304.687231600285"/>
		<Force x="-375.46449515223503" y="226.07227301597595" z="-1126.3326532840729"/>
		<Force x="-7636.2762415371835" y="9930.316313948017" z="-14078.485685318708"/>
		<Force x="1799691.1932382407" y="-506359.21215096023" z="-6312739.484319748"/>
		<Force x="-5786895.213232588" y="2526047.718620979" z="-3841437.326113456"/>
		<Force x="946826036.9779612" y="2147482970.6204963" z="-1387388967.2019086"/>
		<Force x="-5682195.427285664" y="4117227.532124251" z="-4188612.7619630396"/>
		<Force x="-2147482003.5627978" y="-2147483091.2180963" z="2147482447.272242"/>
		<Force x="406368.87545269355" y="91007960.18527931" z="12938035.541174073"/>
		<Force x="-18357.008375559002" y="-8470.551511131227" z="-39213.08100346103"/>
		<Force x="-11353.38977176766" y="32614.992919194978" z="4316.4619162229355"/>
		<Force x="-807.086346781347" y="1307.3315253367182" z="-1319.6034884003457"/>
		<Force x="-1579.4817805821076" y="389.5070983064361" z="-5327.900602178881"/>
		<Force x="-611925183.1597053" y="-2147483293.4665601" z="-1544013898.398549"/>
		<Force x="-13132.101597577566" y="14070.259814377641" z="2703.267372209346"/>
		<Force x="-441.5867026858032" y="284.88290544599295" z="-309.18818758800626"/>
		<Force x="799884.972563623" y="-26272277.146257557" z="-16386863.979574084"/>
		<Force x="-103.70126200653613" y="200.0155048253946" z="307.4402358804364"/>
		<Force x="-157.16462118178606" y="-352.91189059615135" z="374.89725977927446"/>
		<Force x="135.95640646666288" y="1397.6471714824438" z="-1017.9448965117335"/>
		<Force x="-125.75287158042192" y="281.8373593091965" z="404.3270717263222"/>
		<Force x="284.638383788988" y="-315.76603278517723" z="37.13486219197512"/>
		<Force x="-1180.6559161995538" y="879.8535707178526" z="-1076.0392582085915"/>
		<Force x="7107.727981466567" y="-4748.120029971236" z="-260.69231014465913"/>
		<Force x="1173.502292983234" y="-198.51490212976933" z="32.62093308568001"/>
		<Force x="333.4550823494792" y="-617.4722494538873" z="-1414.2599130505696"/>
		<Force x="-40.12506364285946" y="-391.1407044623047" z="418.76644515246153"/>
		<Force x="164.39684820361435" y="433.36539504118264" z="-640.1045698840171"/>
		<Force x="1137.1840524573345" y="-13.361711234087124" z="-419.0570596754551"/>
		<Force x="-4461.869703186676" y="-2016.5941753722727" z="872.0975563237444"/>
		<Force x="2080.688593586907" y="787.2509435014799" z="349.25279674492776"/>
		<Force x="748.8276197835803" y="102.4979001507163" z="1004.2751858793199"/>
		<Force x="1165.0617133199703" y="750.8885315053631" z="-1982.1183662754484"/>
		<Force x="-516.1687885075808" y="38.08993250876665" z="-289.2939518019557"/>
		<Force x="-221.00652071088552" y="197.17078682780266" z="548.0083630187437"/>
		<Force x="-456.6598231717944" y="-127.42054602410644" z="255.71411358378828"/>
		<Force x="379.5441285818815" y="-54.64709198102355" z="293.5244851382449"/>
		<Force x="-425.58521872758865" y="77.29560938850045" z="-196.87423714250326"/>
		<Force x="462.48079481720924" y="153.31016566883773" z="-143.38972356915474"/>
		<Force x="455.44269558787346" y="-221.92452642321587" z="134.71835344284773"/>
		<Force x="-430.8738071322441" y="-235.99550517648458" z="311.48662201315165"/>
	</Forces>
</State>
