{
    "monomers": {
        "ethane-1,2-diol_TERM": [
            "[2*:1]-[#8D2+0:2]-[#6D4+0:3](-[#6D4+0:4](-[#8D2+0:5]-[#1D1+0:10])(-[#1D1+0:8])-[#1D1+0:9])(-[#1D1+0:6])-[#1D1+0:7]"
        ],
        "naphthalene-2,6-dicarboxylic acid_TERM": [
            "[*:1]-[#6D3+0:2](=[#8D1+0:3])-[#6D3+0:4]1=[#6D3+0:5](-[#1D1+0:17])-[#6D3+0:6](-[#1D1+0:18])=[#6D3+0:7]2-[#6D3+0:8](-[#1D1+0:19])=[#6D3+0:9](-[#6D3+0:10](=[#8D1+0:11])-[#8D2+0:12]-[#1D1+0:20])-[#6D3+0:13](-[#1D1+0:21])=[#6D3+0:14](-[#1D1+0:22])-[#6D3+0:15]-2=[#6D3+0:16]-1-[#1D1+0:23]"
        ],
        "ethane-1,2-diol_MID": [
            "[2*:1]-[#8D2+0:2]-[#6D4+0:3](-[#6D4+0:4](-[#8D2+0:5]-[2*:6])(-[#1D1+0:9])-[#1D1+0:10])(-[#1D1+0:7])-[#1D1+0:8]"
        ],
        "naphthalene-2,6-dicarboxylic acid_MID": [
            "[*:1]-[#6D3+0:2](=[#8D1+0:3])-[#6D3+0:4]1=[#6D3+0:5](-[#1D1+0:17])-[#6D3+0:6](-[#1D1+0:18])=[#6D3+0:7]2-[#6D3+0:8](-[#1D1+0:19])=[#6D3+0:9](-[#6D3+0:10](-[*:11])=[#8D1+0:12])-[#6D3+0:13](-[#1D1+0:20])=[#6D3+0:14](-[#1D1+0:21])-[#6D3+0:15]-2=[#6D3+0:16]-1-[#1D1+0:22]"
        ]
    },
    "term_orient": {}
}