<?xml version="1.0" ?>
<State openmmVersion="8.0" stepCount="0" time="0" type="State" version="1">
	<PeriodicBoxVectors>
		<A x="10" y="0" z="0"/>
		<B x="0" y="10" z="0"/>
		<C x="0" y="0" z="10"/>
	</PeriodicBoxVectors>
	<Parameters/>
	<Energies KineticEnergy="0" PotentialEnergy="1870.897220702734"/>
	<Positions>
		<Position x="-.3730000019073486" y=".07680000066757202" z="-.0671999990940094"/>
		<Position x="-.33289999961853023" y="-.010499999672174453" z=".0430999994277954"/>
		<Position x="-.19730000495910643" y="-.07870000004768371" z=".018000000715255735"/>
		<Position x="-.08000000119209288" y=".02039999961853027" z=".02029999941587448"/>
		<Position x=".054199999570846556" y="-.052999997138977045" z=".009200000017881392"/>
		<Position x=".17130000591278075" y=".04589999914169311" z=".010199999809265135"/>
		<Position x=".3053999900817871" y="-.02720000147819519" z="-.0006000000052154064"/>
		<Position x=".4151999950408935" y=".06890000104904175" z="-.0017000000923871994"/>
		<Position x=".4223000049591064" y=".11150000095367431" z=".09359999895095825"/>
		<Position x=".30769999027252193" y="-.08610000014305114" z="-.09490000009536742"/>
		<Position x=".3176000118255615" y="-.09729999899864196" z=".08510000109672546"/>
		<Position x=".16920000314712522" y=".10470000505447387" z=".10470000505447387"/>
		<Position x=".16130000352859497" y=".11629999876022339" z="-.07530000209808349"/>
		<Position x=".05630000233650207" y="-.11160000562667846" z="-.0852999985218048"/>
		<Position x=".06480000019073485" y="-.12339999675750732" z=".09470000267028808"/>
		<Position x="-.08930000066757202" y=".09120000004768371" z="-.06489999890327453"/>
		<Position x="-.08240000009536742" y=".07839999794960022" z=".11519999504089355"/>
		<Position x="-.18190000057220457" y="-.1546000003814697" z=".0977999985218048"/>
		<Position x="-.19950000047683714" y="-.13229999542236326" z="-.07940000295639038"/>
		<Position x="-.3295000076293945" y=".047900000214576716" z=".13760000467300415"/>
		<Position x="-.4103000164031982" y="-.08920000195503235" z=".05550000071525573"/>
		<Position x="-.31029999256134033" y=".16039999723434448" z="-.06949999928474426"/>
		<Position x=".5056000232696533" y=".01469999998807907" z="-.017399999499320983"/>
		<Position x=".5945000171661377" y=".06520000100135803" z="-.08399999737739562"/>
		<Position x=".5244999885559082" y="-.12209999561309813" z=".04120000004768371"/>
		<Position x=".40100002288818354" y="-.16599999666213988" z=".12079999446868896"/>
		<Position x=".42090001106262204" y="-.3058000087738037" z=".18049999475479125"/>
		<Position x=".2974999904632568" y="-.34969999790191647" z=".25999999046325684"/>
		<Position x=".3164000034332275" y="-.48649997711181636" z=".31860001087188716"/>
		<Position x=".22750000953674315" y="-.5369999885559081" z=".3852999925613403"/>
		<Position x=".27869999408721924" y="-.27769999504089354" z=".3426000118255615"/>
		<Position x=".20859999656677244" y="-.3513000011444091" z=".19320000410079954"/>
		<Position x=".509499979019165" y="-.3049000024795532" z=".2476999998092651"/>
		<Position x=".43949999809265133" y="-.378600001335144" z=".0984000027179718"/>
		<Position x=".38250000476837154" y="-.09319999814033507" z=".20290000438690184"/>
		<Position x=".31240000724792477" y="-.16690000295639038" z=".05350000262260437"/>
		<Position x=".6132999897003173" y="-.12050000429153442" z=".10800000429153442"/>
		<Position x=".5433000087738037" y="-.19409999847412107" z="-.04129999876022339"/>
		<Position x="-.3625" y=".02560000121593475" z="-.1577999949455261"/>
		<Position x="-.2983999967575073" y=".11289999485015868" z="-.25599999427795406"/>
		<Position x="-.17200000286102293" y=".18109999895095824" z="-.20069999694824217"/>
		<Position x="-.05740000009536743" y=".08199999928474426" z="-.17630000114440916"/>
		<Position x=".07080000042915344" y=".15540000200271606" z="-.13489999771118164"/>
		<Position x=".18509999513626096" y=".05649999976158142" z="-.10930000543594359"/>
		<Position x=".3131999969482422" y=".1296000003814697" z="-.06819999814033507"/>
		<Position x=".41979999542236324" y=".03350000083446503" z="-.04210000038146972"/>
		<Position x=".5026999950408935" y=".08669999837875365" z="-.00689999982714653"/>
		<Position x=".4485000133514404" y="-.0090999998152256" z="-.13329999446868895"/>
		<Position x=".2940000057220459" y=".18849999904632567" z=".024199999868869778"/>
		<Position x=".3446000099182129" y=".19969999790191648" z="-.14889999628067016"/>
		<Position x=".20460000038146972" y="-.002300000004470348" z="-.20169999599456787"/>
		<Position x=".1559000015258789" y="-.013899999856948852" z="-.02820000052452087"/>
		<Position x=".05130000114440918" y=".21400001049041747" z="-.04239999949932098"/>
		<Position x=".10060000419616698" y=".22579998970031737" z="-.21570000648498533"/>
		<Position x="-.08579999804496764" y=".011200000345706939" z="-.09539999961853027"/>
		<Position x="-.03810000121593475" y=".023999999463558196" z="-.26919999122619626"/>
		<Position x="-.13890000581741332" y=".25699999332427975" z="-.27499999999999997"/>
		<Position x="-.19639999866485594" y=".2346999883651733" z="-.10640000104904174"/>
		<Position x="-.2734999895095825" y=".05450000166893005" z="-.3473000049591064"/>
		<Position x="-.3710000038146972" y=".19160000085830686" z="-.2858000040054321"/>
		<Position x="-.30209999084472655" y="-.05799999833106994" z="-.14119999408721923"/>
		<Position x=".408400011062622" y="-.5416999816894531" z=".3026999950408935"/>
		<Position x=".497100019454956" y="-.5364999771118164" z=".38650000095367426"/>
		<Position x=".42670001983642575" y="-.622100019454956" z=".1774999976158142"/>
		<Position x=".43740000724792477" y="-.7716000080108641" z=".20940001010894774"/>
		<Position x=".45310001373291015" y="-.854300022125244" z=".0809000015258789"/>
		<Position x=".47059998512268064" y="-1.0038999557495116" z=".10980000495910644"/>
		<Position x=".34539999961853024" y="-1.064799976348877" z=".16510000228881835"/>
		<Position x=".2502000093460083" y="-1.0942999839782714" z=".08809999823570251"/>
		<Position x=".33320000171661374" y="-1.0859000205993652" z=".30209999084472655"/>
		<Position x=".2486999988555908" y="-1.1258000373840331" z=".3411999940872192"/>
		<Position x=".5546000003814697" y="-1.0194999694824218" z=".1809000015258789"/>
		<Position x=".496999979019165" y="-1.0560999870300292" z=".015199999511241912"/>
		<Position x=".5431000232696532" y="-.8187999725341796" z=".02590000033378601"/>
		<Position x=".36489999294281" y="-.8390000343322753" z=".014900000393390653"/>
		<Position x=".5251999855041504" y="-.7892000198364257" z=".2753000020980835"/>
		<Position x=".3456000089645385" y="-.8038000106811523" z=".2634000062942505"/>
		<Position x=".33970000743865963" y="-.6045000076293945" z=".11059999465942381"/>
		<Position x=".5185999870300293" y="-.5875999927520752" z=".12530000209808348"/>
	</Positions>
	<Velocities>
		<Velocity x="0" y="0" z="0"/>
		<Velocity x="0" y="0" z="0"/>
		<Velocity x="0" y="0" z="0"/>
		<Velocity x="0" y="0" z="0"/>
		<Velocity x="0" y="0" z="0"/>
		<Velocity x="0" y="0" z="0"/>
		<Velocity x="0" y="0" z="0"/>
		<Velocity x="0" y="0" z="0"/>
		<Velocity x="0" y="0" z="0"/>
		<Velocity x="0" y="0" z="0"/>
		<Velocity x="0" y="0" z="0"/>
		<Velocity x="0" y="0" z="0"/>
		<Velocity x="0" y="0" z="0"/>
		<Velocity x="0" y="0" z="0"/>
		<Velocity x="0" y="0" z="0"/>
		<Velocity x="0" y="0" z="0"/>
		<Velocity x="0" y="0" z="0"/>
		<Velocity x="0" y="0" z="0"/>
		<Velocity x="0" y="0" z="0"/>
		<Velocity x="0" y="0" z="0"/>
		<Velocity x="0" y="0" z="0"/>
		<Velocity x="0" y="0" z="0"/>
		<Velocity x="0" y="0" z="0"/>
		<Velocity x="0" y="0" z="0"/>
		<Velocity x="0" y="0" z="0"/>
		<Velocity x="0" y="0" z="0"/>
		<Velocity x="0" y="0" z="0"/>
		<Velocity x="0" y="0" z="0"/>
		<Velocity x="0" y="0" z="0"/>
		<Velocity x="0" y="0" z="0"/>
		<Velocity x="0" y="0" z="0"/>
		<Velocity x="0" y="0" z="0"/>
		<Velocity x="0" y="0" z="0"/>
		<Velocity x="0" y="0" z="0"/>
		<Velocity x="0" y="0" z="0"/>
		<Velocity x="0" y="0" z="0"/>
		<Velocity x="0" y="0" z="0"/>
		<Velocity x="0" y="0" z="0"/>
		<Velocity x="0" y="0" z="0"/>
		<Velocity x="0" y="0" z="0"/>
		<Velocity x="0" y="0" z="0"/>
		<Velocity x="0" y="0" z="0"/>
		<Velocity x="0" y="0" z="0"/>
		<Velocity x="0" y="0" z="0"/>
		<Velocity x="0" y="0" z="0"/>
		<Velocity x="0" y="0" z="0"/>
		<Velocity x="0" y="0" z="0"/>
		<Velocity x="0" y="0" z="0"/>
		<Velocity x="0" y="0" z="0"/>
		<Velocity x="0" y="0" z="0"/>
		<Velocity x="0" y="0" z="0"/>
		<Velocity x="0" y="0" z="0"/>
		<Velocity x="0" y="0" z="0"/>
		<Velocity x="0" y="0" z="0"/>
		<Velocity x="0" y="0" z="0"/>
		<Velocity x="0" y="0" z="0"/>
		<Velocity x="0" y="0" z="0"/>
		<Velocity x="0" y="0" z="0"/>
		<Velocity x="0" y="0" z="0"/>
		<Velocity x="0" y="0" z="0"/>
		<Velocity x="0" y="0" z="0"/>
		<Velocity x="0" y="0" z="0"/>
		<Velocity x="0" y="0" z="0"/>
		<Velocity x="0" y="0" z="0"/>
		<Velocity x="0" y="0" z="0"/>
		<Velocity x="0" y="0" z="0"/>
		<Velocity x="0" y="0" z="0"/>
		<Velocity x="0" y="0" z="0"/>
		<Velocity x="0" y="0" z="0"/>
		<Velocity x="0" y="0" z="0"/>
		<Velocity x="0" y="0" z="0"/>
		<Velocity x="0" y="0" z="0"/>
		<Velocity x="0" y="0" z="0"/>
		<Velocity x="0" y="0" z="0"/>
		<Velocity x="0" y="0" z="0"/>
		<Velocity x="0" y="0" z="0"/>
		<Velocity x="0" y="0" z="0"/>
		<Velocity x="0" y="0" z="0"/>
		<Velocity x="0" y="0" z="0"/>
	</Velocities>
	<Forces>
		<Force x="-563.9495824037033" y="7060.660518311973" z="11339.278804511188"/>
		<Force x="-600.9458195485174" y="-199.69315047752207" z="933.6030228300137"/>
		<Force x="446.94357341295904" y="-798.1437528057106" z="316.13308271271785"/>
		<Force x="4.600217368639591" y="598.7194305268374" z="-53.26445705726326"/>
		<Force x="87.15154459728831" y="-640.3768586159324" z="-38.57820093222119"/>
		<Force x="-150.65609865233134" y="372.84448403573697" z="160.31348757182343"/>
		<Force x="-2090.603062959966" y="695.4378706703644" z="-591.3575244457514"/>
		<Force x="-9602.79520928842" y="21250.944566050443" z="19658.991905842275"/>
		<Force x="-551.1709775870904" y="-538.0530152471761" z="-2008.4748403179212"/>
		<Force x="-219.5886124834998" y="186.13042635139993" z="425.63546595975373"/>
		<Force x="-158.1931802228114" y="334.1249754437731" z="-378.9252572111045"/>
		<Force x="-.8850792563730039" y="-258.32297217914714" z="-517.3034199490457"/>
		<Force x="83.04329077949558" y="-532.4072241085837" z="204.6276321508933"/>
		<Force x="-5.491152528941129" y="217.82492521735293" z="448.69656803961084"/>
		<Force x="-63.219022502838925" y="278.9391052656388" z="-431.1581888415142"/>
		<Force x="-28.221951348395294" y="-144.91308280488005" z="344.8120593898915"/>
		<Force x="-15.07834027876859" y="-220.1329236863596" z="-471.4223647781389"/>
		<Force x="-60.98922720131128" y="341.94362960818086" z="-382.44161239283153"/>
		<Force x="24.018622353812695" y="225.3026586173669" z="502.2716333857394"/>
		<Force x="-19.67027086658071" y="-274.65315696177055" z="-398.49002737682895"/>
		<Force x="265.42256464266126" y="300.59269922970736" z="41.480774461972516"/>
		<Force x="-788.7269143064244" y="-560.4247687112434" z="470.7459828337033"/>
		<Force x="1930.7314050189016" y="-9704.63310878665" z="-5053.370847280459"/>
		<Force x="-621.2183891391724" y="413.0804758924404" z="979.1003427071598"/>
		<Force x="2687.4076499279554" y="-1958.1174787803566" z="601.5753128967792"/>
		<Force x="-624.7461176329699" y="-254.50043650446275" z="418.5439354342213"/>
		<Force x="544.5915011751626" y="264.98543261849954" z="-459.859567517502"/>
		<Force x="-848.9052243018173" y="1278.507354045574" z="-386.2174890227451"/>
		<Force x="-7274.859943001469" y="3870.4268229372424" z="1954.710937918198"/>
		<Force x="-1170.5871250555642" y="183.43806870331582" z="25.26820628462059"/>
		<Force x="55.38559134590369" y="-409.4104789641349" z="-363.7065221688847"/>
		<Force x="411.6375748454417" y="-2.99354843097899" z="421.02619877494686"/>
		<Force x="-327.94438398401695" y="-52.964450585627816" z="-300.6063860051259"/>
		<Force x="-1.1841697286823063" y="357.4638528419661" z="399.08578075647137"/>
		<Force x="22.723416777281557" y="-334.12624546243865" z="-410.3272880698159"/>
		<Force x="395.22208898626246" y="26.574509812037036" z="305.8489981536654"/>
		<Force x="-424.0208882844721" y="23.351936702563187" z="-416.8769578681925"/>
		<Force x="-51.56126733661068" y="455.36639972290305" z="412.2875022131768"/>
		<Force x="2002.1495176859135" y="-7047.974544447479" z="-11153.677744789999"/>
		<Force x="-346.9196825913481" y="212.02935688849809" z="-1088.709009859577"/>
		<Force x="453.41443921174596" y="811.9580324191318" z="-237.84727468071935"/>
		<Force x="27.668245695141167" y="-609.0815545904707" z="89.52038932912075"/>
		<Force x="52.983094493922835" y="619.7632047319033" z="62.66750728796433"/>
		<Force x="20.692397395745644" y="-404.1734022535179" z="-72.85471547089514"/>
		<Force x="-346.25319256971494" y="617.8610564588813" z="212.92636113232845"/>
		<Force x="11502.61041017051" y="-16449.80205656538" z="-13180.723942646955"/>
		<Force x="-1678.5667262604395" y="5103.7958210705365" z="-1023.9806611462341"/>
		<Force x="-459.7492036177788" y="614.06550394733" z="177.00362402330597"/>
		<Force x="65.78689191519011" y="-207.10687151089888" z="-535.9513790217413"/>
		<Force x="-145.48694168748625" y="-296.3722671736342" z="429.0108631816456"/>
		<Force x="-98.19043495254438" y="257.3510439614428" z="477.23714388770065"/>
		<Force x="124.08519524904304" y="550.2451518683637" z="-224.70557005115631"/>
		<Force x="104.23289852327768" y="-212.98649051166888" z="-446.85118663297214"/>
		<Force x="-143.10181199361435" y="-266.1131427894736" z="398.77946508958803"/>
		<Force x="47.86882975471924" y="151.7755948025591" z="-353.0115852776222"/>
		<Force x="-119.86229124853111" y="217.43708706241927" z="443.6395609541262"/>
		<Force x="-140.99518560160524" y="-352.2661535495019" z="376.1218686847791"/>
		<Force x="147.8549228096934" y="-221.43778826288616" z="-476.9125220727841"/>
		<Force x="-116.18737143709146" y="280.9831652966733" z="402.0744199855543"/>
		<Force x="281.47065102789145" y="-313.3426987191936" z="33.08800766640519"/>
		<Force x="-638.641848159737" y="543.7021511070918" z="-641.3001811039611"/>
		<Force x="7177.439319720163" y="-4540.395657006343" z="-390.5217975826424"/>
		<Force x="1171.0711958396594" y="-146.8255274980848" z="-29.404381387400406"/>
		<Force x="343.209433443631" y="-344.34815249973815" z="-1468.1947719268646"/>
		<Force x="-38.8279012283586" y="-403.3427504912569" z="422.64450968514575"/>
		<Force x="166.1396677038042" y="424.539346044271" z="-645.5221588327728"/>
		<Force x="1138.0769880022551" y="-19.367069966269696" z="-420.82686950431054"/>
		<Force x="-4462.689629384442" y="-1968.3242632777124" z="891.8306448282067"/>
		<Force x="2081.3169403398915" y="789.5607609578514" z="342.14902838880846"/>
		<Force x="749.6018966643574" y="117.19345967498498" z="1002.3613850458698"/>
		<Force x="1165.078858553441" y="750.8995561391664" z="-1982.1252770901424"/>
		<Force x="-517.0546031004255" y="49.8843667623928" z="-283.8059950294648"/>
		<Force x="-220.74281653344497" y="195.68754012301832" z="547.11277163473"/>
		<Force x="-455.59373775191114" y="-116.30261251429064" z="258.51148171516434"/>
		<Force x="372.5249217425706" y="-57.935957197099796" z="298.40293403603516"/>
		<Force x="-423.3272732253975" y="91.66138075905688" z="-189.8445621404581"/>
		<Force x="460.66388015148726" y="85.68640981621462" z="-159.93770375406842"/>
		<Force x="460.77724670898397" y="-196.25954768750708" z="142.14258139568085"/>
		<Force x="-458.1810248913201" y="-165.1032911031601" z="297.8402964827738"/>
	</Forces>
</State>
