<?xml version="1.0" ?>
<State openmmVersion="8.0" stepCount="0" time="0" type="State" version="1">
	<PeriodicBoxVectors>
		<A x="10" y="0" z="0"/>
		<B x="0" y="10" z="0"/>
		<C x="0" y="0" z="10"/>
	</PeriodicBoxVectors>
	<Parameters/>
	<Energies KineticEnergy="0" PotentialEnergy="21844.200399965495"/>
	<Positions>
		<Position x="-.4948997497558594" y=".20250001549720764" z="-.16460037231445312"/>
		<Position x="-.3698997497558594" y=".15410000085830688" z="-.1266002655029297"/>
		<Position x="-.2578001022338867" y=".2249000072479248" z="-.15159988403320312"/>
		<Position x="-.2634000778198242" y=".3206000030040741" z="-.20180034637451172"/>
		<Position x="-.12549972534179688" y=".17180000245571136" z="-.11120033264160156"/>
		<Position x="-.03520011901855469" y=".2273000031709671" z="-.13309955596923828"/>
		<Position x="-.11999988555908203" y=".05350000411272049" z="-.04810047149658203"/>
		<Position x="-.23999977111816406" y="-.02240000106394291" z="-.02019977569580078"/>
		<Position x="-.3605995178222656" y=".02280000038444996" z="-.057999610900878906"/>
		<Position x="-.4500999450683594" y="-.03529999777674675" z="-.03950023651123047"/>
		<Position x="-.20759963989257812" y="-.15240000188350677" z=".04669952392578125"/>
		<Position x="-.23149967193603516" y="-.26889997720718384" z="-.05099964141845703"/>
		<Position x="-.3388996124267578" y="-.2750999927520752" z="-.07900047302246094"/>
		<Position x="-.20199966430664062" y="-.3652999997138977" z="-.004199981689453125"/>
		<Position x="-.17199993133544922" y="-.25519999861717224" z="-.14389991760253906"/>
		<Position x="-.2911996841430664" y="-.17170000076293945" z=".17459964752197266"/>
		<Position x="-.3990001678466797" y="-.1832999885082245" z=".1500997543334961"/>
		<Position x="-.27989959716796875" y="-.08429999649524689" z=".24230003356933594"/>
		<Position x="-.2578001022338867" y="-.262800008058548" z=".22879981994628906"/>
		<Position x="-.05570030212402344" y="-.13910000026226044" z=".08049964904785156"/>
		<Position x="-.0005998611450195312" y="-.233800008893013" z=".062000274658203125"/>
		<Position x="-.04319953918457031" y="-.11829999834299088" z=".18920040130615234"/>
		<Position x=".0016002655029296875" y="-.020100001245737076" z="-.0024995803833007812"/>
		<Position x=".09420013427734375" y=".06499999761581421" z=".0782003402709961"/>
		<Position x=".06389999389648438" y=".14149999618530273" z=".18410015106201172"/>
		<Position x="-.03800010681152344" y=".14919999241828918" z=".21979999542236328"/>
		<Position x=".17309951782226562" y=".2150000035762787" z=".2523002624511719"/>
		<Position x=".14999961853027344" y=".2778000235557556" z=".3374004364013672"/>
		<Position x=".30010032653808594" y=".20309999585151672" z=".2091999053955078"/>
		<Position x=".40180015563964844" y=".2721000015735626" z=".27449989318847656"/>
		<Position x=".33100032806396484" y=".11640000343322754" z=".0924997329711914"/>
		<Position x=".43309974670410156" y=".10490000247955322" z=".058699607849121094"/>
		<Position x=".2302999496459961" y=".05260000377893448" z=".03079986572265625"/>
		<Position x=".2390003204345703" y="-.04149999842047691" z="-.08539962768554688"/>
		<Position x=".3144998550415039" y=".022499999031424522" z="-.20349979400634766"/>
		<Position x=".42129993438720703" y=".03920000046491623" z="-.1779003143310547"/>
		<Position x=".26920032501220703" y=".12039999663829803" z="-.23040008544921875"/>
		<Position x=".3100004196166992" y="-.04410000145435333" z="-.2924003601074219"/>
		<Position x=".3081998825073242" y="-.1720000058412552" z="-.042099952697753906"/>
		<Position x=".3095998764038086" y="-.24469999969005585" z="-.12600040435791016"/>
		<Position x=".4131002426147461" y="-.15230000019073486" z="-.011099815368652344"/>
		<Position x=".25459957122802734" y="-.21819999814033508" z=".04360008239746094"/>
		<Position x=".08950042724609375" y="-.06790000200271606" z="-.1220998764038086"/>
		<Position x=".07129955291748047" y="-.1745000034570694" z="-.14789962768554688"/>
		<Position x=".06260013580322266" y="-.010300000198185444" z="-.21360015869140625"/>
		<Position x=".501500129699707" y=".26440000534057617" z=".24289989471435547"/>
		<Position x=".5626001358032227" y=".1599999964237213" z=".2585000991821289"/>
		<Position x="-.5053997039794922" y=".29170000553131104" z="-.211700439453125"/>
		<Position x="-.40869998931884766" y=".3400999903678894" z="-.29940032958984375"/>
		<Position x="-.296600341796875" y=".26930001378059387" z="-.32470035552978516"/>
		<Position x="-.2802000045776367" y=".1735999882221222" z="-.2769002914428711"/>
		<Position x="-.1941995620727539" y=".3224000036716461" z="-.41769981384277344"/>
		<Position x="-.10319995880126953" y=".2667999863624573" z="-.43649959564208984"/>
		<Position x="-.2161998748779297" y=".4406000077724457" z="-.4771003723144531"/>
		<Position x="-.336700439453125" y=".5164999961853027" z="-.45110034942626953"/>
		<Position x="-.4295997619628906" y=".47140002250671387" z="-.3654003143310547"/>
		<Position x="-.5184001922607422" y=".5293999910354614" z="-.3438997268676758"/>
		<Position x="-.33590030670166016" y=".6464999914169312" z="-.5254001617431641"/>
		<Position x="-.3157997131347656" y=".7631000280380249" z="-.4267997741699219"/>
		<Position x="-.4010000228881836" y=".7692999839782715" z="-.3556995391845703"/>
		<Position x="-.3091001510620117" y=".8593999743461609" z="-.4818000793457031"/>
		<Position x="-.22229957580566406" y=".7493000030517578" z="-.3683004379272461"/>
		<Position x="-.4661998748779297" y=".6658999919891357" z="-.6052999496459961"/>
		<Position x="-.5530996322631836" y=".6775000095367432" z="-.5371999740600586"/>
		<Position x="-.48489952087402344" y=".578499972820282" z="-.6714000701904297"/>
		<Position x="-.45909976959228516" y=".7570000290870667" z="-.6686000823974609"/>
		<Position x="-.21310043334960938" y=".6331999897956848" z="-.6209001541137695"/>
		<Position x="-.15530014038085938" y=".7280000448226929" z="-.6276998519897461"/>
		<Position x="-.24810028076171875" y=".612500011920929" z="-.7244997024536133"/>
		<Position x="-.1256999969482422" y=".5142999887466431" z="-.5703001022338867"/>
		<Position x="-.07649993896484375" y=".4291999936103821" z="-.6827001571655273"/>
		<Position x="-.14910030364990234" y=".35269999504089355" z="-.7656002044677734"/>
		<Position x="-.256500244140625" y=".3449999988079071" z="-.7544002532958984"/>
		<Position x="-.07960033416748047" y=".27920001745224" z="-.8739004135131836"/>
		<Position x="-.13679981231689453" y=".21639999747276306" z="-.9409999847412109"/>
		<Position x=".05370044708251953" y=".29100000858306885" z="-.8892002105712891"/>
		<Position x=".11779975891113281" y=".22209998965263367" z="-.9917001724243164"/>
		<Position x=".21790027618408203" y=".22950001060962677" z="-1.0052003860473633"/>
		<Position x=".131500244140625" y=".37780001759529114" z="-.7968997955322266"/>
		<Position x=".23830032348632812" y=".38929998874664307" z="-.8099002838134766"/>
		<Position x=".06680011749267578" y=".4415999948978424" z="-.6981000900268555"/>
		<Position x=".12430000305175781" y=".5356000065803528" z="-.5966997146606445"/>
		<Position x=".24300003051757812" y=".4717000126838684" z="-.5221004486083984"/>
		<Position x=".3285999298095703" y=".45500001311302185" z="-.5909004211425781"/>
		<Position x=".21360015869140625" y=".37379997968673706" z="-.4785003662109375"/>
		<Position x=".2769002914428711" y=".5382999777793884" z="-.43990039825439453"/>
		<Position x=".16839981079101562" y=".6660999655723572" z="-.6654996871948242"/>
		<Position x=".20549964904785156" y=".7389000058174133" z="-.5901002883911133"/>
		<Position x=".25" y=".6464000344276428" z="-.7383003234863281"/>
		<Position x=".08329963684082031" y=".7124000191688538" z="-.7201004028320312"/>
		<Position x=".0048999786376953125" y=".5619999766349792" z="-.49969959259033203"/>
		<Position x="-.0006999969482421875" y=".6686999797821045" z="-.4686002731323242"/>
		<Position x=".01959991455078125" y=".5045000314712524" z="-.4055004119873047"/>
		<Position x=".5502996444702148" y=".34929999709129333" z=".19629955291748047"/>
		<Position x=".4868001937866211" y=".45069998502731323" z=".1726999282836914"/>
		<Position x=".7204999923706055" y=".3407999873161316" z=".1549997329711914"/>
	</Positions>
	<Velocities>
		<Velocity x="0" y="0" z="0"/>
		<Velocity x="0" y="0" z="0"/>
		<Velocity x="0" y="0" z="0"/>
		<Velocity x="0" y="0" z="0"/>
		<Velocity x="0" y="0" z="0"/>
		<Velocity x="0" y="0" z="0"/>
		<Velocity x="0" y="0" z="0"/>
		<Velocity x="0" y="0" z="0"/>
		<Velocity x="0" y="0" z="0"/>
		<Velocity x="0" y="0" z="0"/>
		<Velocity x="0" y="0" z="0"/>
		<Velocity x="0" y="0" z="0"/>
		<Velocity x="0" y="0" z="0"/>
		<Velocity x="0" y="0" z="0"/>
		<Velocity x="0" y="0" z="0"/>
		<Velocity x="0" y="0" z="0"/>
		<Velocity x="0" y="0" z="0"/>
		<Velocity x="0" y="0" z="0"/>
		<Velocity x="0" y="0" z="0"/>
		<Velocity x="0" y="0" z="0"/>
		<Velocity x="0" y="0" z="0"/>
		<Velocity x="0" y="0" z="0"/>
		<Velocity x="0" y="0" z="0"/>
		<Velocity x="0" y="0" z="0"/>
		<Velocity x="0" y="0" z="0"/>
		<Velocity x="0" y="0" z="0"/>
		<Velocity x="0" y="0" z="0"/>
		<Velocity x="0" y="0" z="0"/>
		<Velocity x="0" y="0" z="0"/>
		<Velocity x="0" y="0" z="0"/>
		<Velocity x="0" y="0" z="0"/>
		<Velocity x="0" y="0" z="0"/>
		<Velocity x="0" y="0" z="0"/>
		<Velocity x="0" y="0" z="0"/>
		<Velocity x="0" y="0" z="0"/>
		<Velocity x="0" y="0" z="0"/>
		<Velocity x="0" y="0" z="0"/>
		<Velocity x="0" y="0" z="0"/>
		<Velocity x="0" y="0" z="0"/>
		<Velocity x="0" y="0" z="0"/>
		<Velocity x="0" y="0" z="0"/>
		<Velocity x="0" y="0" z="0"/>
		<Velocity x="0" y="0" z="0"/>
		<Velocity x="0" y="0" z="0"/>
		<Velocity x="0" y="0" z="0"/>
		<Velocity x="0" y="0" z="0"/>
		<Velocity x="0" y="0" z="0"/>
		<Velocity x="0" y="0" z="0"/>
		<Velocity x="0" y="0" z="0"/>
		<Velocity x="0" y="0" z="0"/>
		<Velocity x="0" y="0" z="0"/>
		<Velocity x="0" y="0" z="0"/>
		<Velocity x="0" y="0" z="0"/>
		<Velocity x="0" y="0" z="0"/>
		<Velocity x="0" y="0" z="0"/>
		<Velocity x="0" y="0" z="0"/>
		<Velocity x="0" y="0" z="0"/>
		<Velocity x="0" y="0" z="0"/>
		<Velocity x="0" y="0" z="0"/>
		<Velocity x="0" y="0" z="0"/>
		<Velocity x="0" y="0" z="0"/>
		<Velocity x="0" y="0" z="0"/>
		<Velocity x="0" y="0" z="0"/>
		<Velocity x="0" y="0" z="0"/>
		<Velocity x="0" y="0" z="0"/>
		<Velocity x="0" y="0" z="0"/>
		<Velocity x="0" y="0" z="0"/>
		<Velocity x="0" y="0" z="0"/>
		<Velocity x="0" y="0" z="0"/>
		<Velocity x="0" y="0" z="0"/>
		<Velocity x="0" y="0" z="0"/>
		<Velocity x="0" y="0" z="0"/>
		<Velocity x="0" y="0" z="0"/>
		<Velocity x="0" y="0" z="0"/>
		<Velocity x="0" y="0" z="0"/>
		<Velocity x="0" y="0" z="0"/>
		<Velocity x="0" y="0" z="0"/>
		<Velocity x="0" y="0" z="0"/>
		<Velocity x="0" y="0" z="0"/>
		<Velocity x="0" y="0" z="0"/>
		<Velocity x="0" y="0" z="0"/>
		<Velocity x="0" y="0" z="0"/>
		<Velocity x="0" y="0" z="0"/>
		<Velocity x="0" y="0" z="0"/>
		<Velocity x="0" y="0" z="0"/>
		<Velocity x="0" y="0" z="0"/>
		<Velocity x="0" y="0" z="0"/>
		<Velocity x="0" y="0" z="0"/>
		<Velocity x="0" y="0" z="0"/>
		<Velocity x="0" y="0" z="0"/>
		<Velocity x="0" y="0" z="0"/>
		<Velocity x="0" y="0" z="0"/>
		<Velocity x="0" y="0" z="0"/>
		<Velocity x="0" y="0" z="0"/>
		<Velocity x="0" y="0" z="0"/>
		<Velocity x="0" y="0" z="0"/>
	</Velocities>
	<Forces>
		<Force x="1173.5337985919323" y="-11010.842078235932" z="5488.191167037934"/>
		<Force x="-17489.075251011178" y="-8750.602864999324" z="29853.83137699077"/>
		<Force x="168778.18848048872" y="210303.67273022234" z="855133.0567876175"/>
		<Force x="194275.42247102968" y="265253.3650153815" z="652402.1264947923"/>
		<Force x="-1516.3385922852904" y="2195.940642911941" z="-425.94621892273426"/>
		<Force x="187.94920554291457" y="62.537059493362904" z="60.7515694363974"/>
		<Force x="-1910.93064311333" y="-2684.433690115344" z="1109.5924801458605"/>
		<Force x="3102.6015066425316" y="198.29775977507234" z="69.96075151138939"/>
		<Force x="-1449.6603563162498" y="3086.7659109514207" z="-1686.055574208498"/>
		<Force x="-52.25612024310976" y="33.9322060495615" z="7.811309760902077"/>
		<Force x="258.4371291641146" y="-122.18602694571018" z="98.0827123299241"/>
		<Force x="-88.05115548870526" y="-371.51407542824745" z="-228.96938058407977"/>
		<Force x="527.6216633357108" y="41.74226392805576" z="128.2588150948286"/>
		<Force x="-142.68870297446847" y="462.5537340361625" z="-238.2031377556268"/>
		<Force x="-291.20138232875615" y="-33.35626820102334" z="452.91548330150545"/>
		<Force x="-204.0085183084011" y="-154.69384734332561" z="340.9672317057848"/>
		<Force x="533.1095840483904" y="70.42404667288065" z="116.32095716986805"/>
		<Force x="-50.40304081514478" y="-391.5324541926384" z="-333.91607281565666"/>
		<Force x="-169.8389479382895" y="443.48482528328896" z="-246.01504862308502"/>
		<Force x="80.56659712083638" y="-165.7612803503871" z="495.0057590883225"/>
		<Force x="-276.2032879963517" y="504.99449549615383" z="-47.53857496497221"/>
		<Force x="-95.02480247057974" y="-25.040934782475233" z="-611.6933759567328"/>
		<Force x="87.64145448990166" y="-347.6103756055236" z="-44.36240208148956"/>
		<Force x="2567.489529724" y="-1215.663826154545" z="-2016.7072799257003"/>
		<Force x="1591.9375994838774" y="2266.2291269749403" z="2487.4739526584744"/>
		<Force x="-180.13913400284946" y="-1.7446298636496067" z="-45.90213729417883"/>
		<Force x="-3450.9373449990526" y="-1185.5229166597128" z="-710.8511987691745"/>
		<Force x="165.3726332683582" y="77.37927901837975" z="48.25244641676545"/>
		<Force x="3190.687419684604" y="-1492.953717816621" z="-2374.8099896276835"/>
		<Force x="-9771.143568734638" y="-554.3410732392222" z="3999.8819716004655"/>
		<Force x="-234.83917182311416" y="2131.193997973576" z="2505.1706108069047"/>
		<Force x="-49.92290436755866" y="-159.45707844849676" z="-236.38153307372704"/>
		<Force x="-2981.1957885753363" y="-877.9681994784623" z="-260.2701571434736"/>
		<Force x="-196.85765039548278" y="-136.1673302091658" z="-174.53997813165188"/>
		<Force x="165.6805697977543" y="76.5388146340847" z="-358.5210115686059"/>
		<Force x="-504.16147861257195" y="-68.63960455358028" z="-107.99633341282606"/>
		<Force x="218.0556136071682" y="-461.94097607862204" z="146.00483260303736"/>
		<Force x="31.0858813226223" y="342.94639414851554" z="421.41591038554907"/>
		<Force x="193.19616830721498" y="-343.3113774806261" z="87.877192735672"/>
		<Force x="4.878289169631898" y="322.148657515645" z="387.5529086077586"/>
		<Force x="-501.894392862916" y="-87.07482777908444" z="-133.36666390299797"/>
		<Force x="260.202337263152" y="246.3759853122756" z="-394.52282108180225"/>
		<Force x="-67.57692312076688" y="18.316278487443924" z="-558.9488071575761"/>
		<Force x="98.99592789728194" y="522.2619122117758" z="274.9904875308275"/>
		<Force x="154.75011609494686" y="-241.1324236765504" z="563.5847085788846"/>
		<Force x="2078.5356528202537" y="-9376.945906619076" z="2259.6090951589867"/>
		<Force x="1238.2373830582947" y="-652.941067641601" z="146.27558540552855"/>
		<Force x="-1315.8284727074206" y="11004.743849352002" z="-5441.990950334817"/>
		<Force x="-28511.497272757813" y="8752.837397065014" z="-19552.22521736659"/>
		<Force x="-211956.40418641083" y="-209845.84844833054" z="-844350.8848453197"/>
		<Force x="-102811.30863906513" y="-265709.64287857874" z="-674007.4707454161"/>
		<Force x="-1179.6076481752098" y="-2233.047501217574" z="1042.8173492848873"/>
		<Force x="136.72314827516675" y="-38.420198772102594" z="-153.11423008842394"/>
		<Force x="-2215.9789917685557" y="2727.9054702294525" z="-196.7759340426419"/>
		<Force x="2794.952327268664" y="-196.580042373389" z="-1385.35749542946"/>
		<Force x="-578.3870520405471" y="-3116.8826986029744" z="2149.2318155542016"/>
		<Force x="-66.34185492619872" y="-14.988833509385586" z="14.656573680695146"/>
		<Force x="154.03235577605665" y="149.28028705716133" z="-189.79512353707105"/>
		<Force x="16.583117719739676" y="325.8742904216051" z="212.25442595034838"/>
		<Force x="424.0565623193979" y="-38.7989706248045" z="-332.5966226607561"/>
		<Force x="-23.527447106782347" y="-448.06850283034146" z="275.54109693691134"/>
		<Force x="-454.81019891798496" y="40.70146534591913" z="-276.20886275172234"/>
		<Force x="-283.1209217682481" y="141.0267028659582" z="-259.6439186120406"/>
		<Force x="400.0439464151859" y="-66.22509279916994" z="-305.1277313930914"/>
		<Force x="98.52886410057545" y="398.711948024109" z="330.3977875225246"/>
		<Force x="-48.382274768315256" y="-447.6755616753362" z="300.1581219860818"/>
		<Force x="-85.09399901703" y="224.19155121594667" z="-453.2311989367008"/>
		<Force x="-248.77084458991885" y="-541.9057756066322" z="161.6170862019062"/>
		<Force x="166.70452283788472" y="8.787210170179605" z="569.7568445950747"/>
		<Force x="81.86002293787897" y="313.8329295143485" z="12.64849666133523"/>
		<Force x="3200.061714864336" y="1195.1002045711502" z="680.1767862141132"/>
		<Force x="357.85219262260944" y="-2261.1386741306633" z="-2908.675608795136"/>
		<Force x="-111.25075218081474" y="9.351128526031971" z="113.00730205327272"/>
		<Force x="-2579.2038243282586" y="1134.5465649387334" z="2034.0480456145015"/>
		<Force x="157.97686153044924" y="-44.05495412182063" z="-108.85571038071066"/>
		<Force x="4017.6286600013264" y="1516.2997919805348" z="1016.5812399480492"/>
		<Force x="701.3664341999684" y="-320.68528530607" z="-574.7860878384672"/>
		<Force x="-1970.4655064134859" y="566.8085594053846" z="1165.4430495074484"/>
		<Force x="-908.9086263845675" y="-2635.823931227438" z="-3062.2084550261497"/>
		<Force x="-11.445208573713899" y="-44.143208999419585" z="-21.79640679433942"/>
		<Force x="-2559.8055619075894" y="867.0864007789642" z="1511.161981716752"/>
		<Force x="-80.5053434483707" y="159.29452070966363" z="224.32798666507006"/>
		<Force x="322.38808922842145" y="-83.6080954670906" z="239.98636904358864"/>
		<Force x="-424.3999002724886" y="68.84042319608852" z="308.6136161731556"/>
		<Force x="123.38942674919963" y="457.41514636576176" z="-227.85700629651546"/>
		<Force x="-149.57923340052366" y="-329.99786834418774" z="-376.6214526668191"/>
		<Force x="135.55791737884283" y="412.5505494400859" z="-111.32610239833593"/>
		<Force x="-175.39873905479908" y="-359.66423407197" z="-387.75150146428496"/>
		<Force x="-403.898420272395" y="72.9204663168639" z="335.03925874689594"/>
		<Force x="416.7571528716944" y="-273.0528708938509" z="253.0067239413038"/>
		<Force x="124.52767667733133" y="55.031586579978466" z="555.8190171644092"/>
		<Force x="-10.295271590352058" y="-556.9506260380149" z="-305.61960719525814"/>
		<Force x="-92.08214317634702" y="225.55543445795774" z="-567.6626191958785"/>
		<Force x="4584.0501958318055" y="6855.49631462805" z="-3525.4612502465025"/>
		<Force x="1149.1431455281563" y="3575.0725521789864" z="-1917.5545058362186"/>
		<Force x="402.2568695922382" y="600.2138682720251" z="-355.2158807106316"/>
	</Forces>
</State>
