<?xml version="1.0" ?>
<State openmmVersion="8.0" stepCount="0" time="0" type="State" version="1">
	<PeriodicBoxVectors>
		<A x="10" y="0" z="0"/>
		<B x="0" y="10" z="0"/>
		<C x="0" y="0" z="10"/>
	</PeriodicBoxVectors>
	<Parameters/>
	<Energies KineticEnergy="0" PotentialEnergy="26699950.251403116"/>
	<Positions>
		<Position x=".15760000050067902" y="-.03359999880194664" z=".08570003509521484"/>
		<Position x=".06359999626874924" y="-.04190000146627426" z="-.017900466918945312"/>
		<Position x="-.07189999520778656" y=".010999999940395355" z=".029000282287597656"/>
		<Position x="-.16749998927116394" y="-.003599999938160181" z="-.07240009307861328"/>
		<Position x="-.10509999841451645" y="-.04690000042319298" z=".11769962310791016"/>
		<Position x="-.06309999525547028" y=".11799999326467514" z=".058899879455566406"/>
		<Position x=".05299999564886093" y="-.14839999377727509" z="-.047699928283691406"/>
		<Position x=".09870000183582306" y=".015399999916553497" z="-.10680007934570312"/>
		<Position x="-.14900000393390656" y=".0714000016450882" z="-.14169979095458984"/>
		<Position x="-.23910000920295715" y=".10429999977350235" z="-.22319984436035156"/>
		<Position x="-.019099999219179153" y=".1387999951839447" z="-.1447000503540039"/>
		<Position x=".08259999752044678" y=".11230000108480453" z="-.06379985809326172"/>
		<Position x=".08449999988079071" y=".03819999843835831" z=".015000343322753906"/>
		<Position x=".1907999962568283" y=".20250001549720764" z="-.10229969024658203"/>
		<Position x=".28929999470710754" y=".20890000462532043" z="-.057700157165527344"/>
		<Position x=".14509999752044678" y=".27560001611709595" z="-.20300006866455078"/>
		<Position x=".2206999957561493" y=".37959998846054077" z="-.27299976348876953"/>
		<Position x=".16770000755786896" y=".44339999556541443" z="-.3676004409790039"/>
		<Position x=".014499999582767487" y=".23989999294281006" z="-.23359966278076172"/>
		<Position x=".18450000882148743" y=".061799995601177216" z=".09200000762939453"/>
		<Position x=".3147999942302704" y=".07009999454021454" z=".04109954833984375"/>
		<Position x=".4152999818325043" y=".01720000058412552" z=".1434001922607422"/>
		<Position x=".5461000204086304" y=".03179999813437462" z=".0951995849609375"/>
		<Position x=".5597000122070312" y="-.03999999910593033" z=".027899742126464844"/>
		<Position x=".40549999475479126" y=".07519999891519547" z=".23760032653808594"/>
		<Position x=".39410001039505005" y="-.08969999849796295" z=".16629981994628906"/>
		<Position x=".3375999927520752" y=".17660000920295715" z=".01920032501220703"/>
		<Position x=".3230000138282776" y=".012800000607967377" z="-.05410003662109375"/>
		<Position x=".3224000036716461" y=".40219998359680176" z="-.2437000274658203"/>
		<Position x=".37770000100135803" y=".5067999958992004" z="-.2867002487182617"/>
		<Position x=".3953999876976013" y=".3118000030517578" z="-.1546001434326172"/>
		<Position x=".3471999764442444" y=".19939999282360077" z="-.1035003662109375"/>
		<Position x=".2484000027179718" y=".15850000083446503" z="-.11989974975585938"/>
		<Position x=".453499972820282" y=".14220000803470612" z="-.02140045166015625"/>
		<Position x=".4491000175476074" y=".050199996680021286" z=".03549957275390625"/>
		<Position x=".5568999648094177" y=".22509999573230743" z="-.02989959716796875"/>
		<Position x=".6864999532699585" y=".20799998939037323" z=".03670024871826172"/>
		<Position x=".7080999612808228" y=".10770000517368317" z=".1099996566772461"/>
		<Position x=".7861000299453735" y=".3033999800682068" z=".0186004638671875"/>
		<Position x=".8762999773025513" y=".29350000619888306" z=".0635995864868164"/>
		<Position x=".5257999897003174" y=".3326999843120575" z="-.11190032958984375"/>
	</Positions>
	<Velocities>
		<Velocity x="0" y="0" z="0"/>
		<Velocity x="0" y="0" z="0"/>
		<Velocity x="0" y="0" z="0"/>
		<Velocity x="0" y="0" z="0"/>
		<Velocity x="0" y="0" z="0"/>
		<Velocity x="0" y="0" z="0"/>
		<Velocity x="0" y="0" z="0"/>
		<Velocity x="0" y="0" z="0"/>
		<Velocity x="0" y="0" z="0"/>
		<Velocity x="0" y="0" z="0"/>
		<Velocity x="0" y="0" z="0"/>
		<Velocity x="0" y="0" z="0"/>
		<Velocity x="0" y="0" z="0"/>
		<Velocity x="0" y="0" z="0"/>
		<Velocity x="0" y="0" z="0"/>
		<Velocity x="0" y="0" z="0"/>
		<Velocity x="0" y="0" z="0"/>
		<Velocity x="0" y="0" z="0"/>
		<Velocity x="0" y="0" z="0"/>
		<Velocity x="0" y="0" z="0"/>
		<Velocity x="0" y="0" z="0"/>
		<Velocity x="0" y="0" z="0"/>
		<Velocity x="0" y="0" z="0"/>
		<Velocity x="0" y="0" z="0"/>
		<Velocity x="0" y="0" z="0"/>
		<Velocity x="0" y="0" z="0"/>
		<Velocity x="0" y="0" z="0"/>
		<Velocity x="0" y="0" z="0"/>
		<Velocity x="0" y="0" z="0"/>
		<Velocity x="0" y="0" z="0"/>
		<Velocity x="0" y="0" z="0"/>
		<Velocity x="0" y="0" z="0"/>
		<Velocity x="0" y="0" z="0"/>
		<Velocity x="0" y="0" z="0"/>
		<Velocity x="0" y="0" z="0"/>
		<Velocity x="0" y="0" z="0"/>
		<Velocity x="0" y="0" z="0"/>
		<Velocity x="0" y="0" z="0"/>
		<Velocity x="0" y="0" z="0"/>
		<Velocity x="0" y="0" z="0"/>
		<Velocity x="0" y="0" z="0"/>
	</Velocities>
	<Forces>
		<Force x="806852.777712822" y="-810193.2193821371" z="787363.9034123123"/>
		<Force x="-42252345.02571373" y="-162436217.027088" z="-66058413.167587414"/>
		<Force x="-122397.30081974342" y="-39993.21688711643" z="33440.55658760667"/>
		<Force x="-352.71061740163714" y="-5150.475796927698" z="5446.274926931597"/>
		<Force x="108.28636942058802" y="241.0800200663507" z="-274.7462730705738"/>
		<Force x="-10004.910701781511" y="573.6770759373903" z="10298.325940795243"/>
		<Force x="-38.7425378896296" y="35.20311053097248" z=".7974500581622124"/>
		<Force x="2807894.0075320676" y="-16728795.512113396" z="-7544491.443706587"/>
		<Force x="-3511.5443093446083" y="4928.112357974984" z="-7713.3232513498515"/>
		<Force x="2009.7953172288835" y="309.5799825079739" z="627.1098296046257"/>
		<Force x="-22817.0468237279" y="33380.49598957971" z="-20981.523678272963"/>
		<Force x="-2674801.5701440987" y="17639388.289005734" z="7045530.725284936"/>
		<Force x="40691731.33656116" y="162170670.66925982" z="65149074.19822456"/>
		<Force x="-1527179643.7942562" y="1165374246.0013847" z="466135752.2201927"/>
		<Force x="-1576498501.190666" y="266483346.35719463" z="1252729785.3405166"/>
		<Force x="-22718.393751546042" y="20189.82344264025" z="-16699.027739507612"/>
		<Force x="-8946.426658419427" y="-681.072528824443" z="-3821.1330489988904"/>
		<Force x="-1459.9375299783424" y="-1359.4931201599538" z="342.6426654430106"/>
		<Force x="531.4342774089891" y="-270.5949208852835" z="559.681925550336"/>
		<Force x="752879.2203663401" y="159838.97760550678" z="608649.1097861808"/>
		<Force x="-1213187.7497990094" y="-229749.55668103136" z="336443.2053185841"/>
		<Force x="-1369038.326073952" y="-1349443.967504859" z="4375824.201902479"/>
		<Force x="3211988.4794252887" y="-748835.0164645463" z="2075874.769387098"/>
		<Force x="768.3634897712618" y="693.069425343303" z="616.736013704678"/>
		<Force x="-45.39929542923346" y="-257.0439576867502" z="-114.53191045881249"/>
		<Force x="93.43575937720016" y="272.3948829565197" z="169.36154548963532"/>
		<Force x="297087.2511273138" y="-1423460.0310659632" z="6602586.001635596"/>
		<Force x="-13816.313952993602" y="-19932.086703449488" z="-2920.1523866653442"/>
		<Force x="9034.965337779606" y="3501.5703440704383" z="1564.3574036639184"/>
		<Force x="1398.910415569786" y="-654.175743099302" z="1269.9885578397661"/>
		<Force x="23731.579287477536" y="20767.028025123756" z="-17036.877289466327"/>
		<Force x="1580848759.375004" y="-258605739.93802884" z="-1251513706.0223377"/>
		<Force x="1520774752.8887985" y="-1171233753.6508098" z="-473408330.5520284"/>
		<Force x="2214965.422186547" y="-179012.46010847762" z="-926779.7452189629"/>
		<Force x="-1163802.7831607908" y="1840775.4633398782" z="-6384852.039450845"/>
		<Force x="2807.305474836845" y="7050.926945607876" z="-4012.144965274958"/>
		<Force x="6390.515958851436" y="2593.99826934305" z="1080.0450646732934"/>
		<Force x="105612.40405862313" y="50958.23011084227" z="8411.221957631176"/>
		<Force x="566.1535920556635" y="1215.5276660453528" z="-566.1019878948573"/>
		<Force x="-2210.6322869362775" y="-922.0027038641274" z="-345.64619225775823"/>
		<Force x="-524.4739287134726" y="-557.5896309609525" z="123.93516411189921"/>
	</Forces>
</State>
